{
  "items": [
    {
      "label": "People",
      "options": [
        {
          "label": "About",
          "href": "/en/pages/People"
        },
        {
          "label": "Search",
          "href": "/en/search/people"
        }
      ],
      "_template": "Dropdown"
    },
    {
      "label": "The Academical Village",
      "options": [
        {
          "label": "About",
          "href": "/en/pages/Academical-Village"
        },
        {
          "label": "Map",
          "href": "/en/search/places/#/&map=0/0/0"
        }
      ],
      "_template": "Dropdown"
    },
    {
      "label": "Essays",
      "href": "/en/posts",
      "_template": "URL"
    },
    {
      "label": "Documents",
      "href": "/en/search/items/",
      "_template": "URL"
    },
    {
      "label": "Images",
      "options": [
        {
          "label": "Galleries",
          "href": "/en/gallery/"
        },
        {
          "label": "Search All",
          "href": "/en/search/images/"
        }
      ],
      "_template": "Dropdown"
    },
    {
      "label": "About",
      "href": "/en/pages/About",
      "_template": "URL"
    }
  ]
}